MANIFEST.in
README.txt
setup.py
XStatic_underscore.egg-info/PKG-INFO
XStatic_underscore.egg-info/SOURCES.txt
XStatic_underscore.egg-info/dependency_links.txt
XStatic_underscore.egg-info/namespace_packages.txt
XStatic_underscore.egg-info/not-zip-safe
XStatic_underscore.egg-info/top_level.txt
xstatic/__init__.py
xstatic/pkg/__init__.py
xstatic/pkg/underscore/__init__.py
xstatic/pkg/underscore/data/.bower.json
xstatic/pkg/underscore/data/.eslintrc
xstatic/pkg/underscore/data/.gitignore
xstatic/pkg/underscore/data/LICENSE
xstatic/pkg/underscore/data/README.md
xstatic/pkg/underscore/data/bower.json
xstatic/pkg/underscore/data/component.json
xstatic/pkg/underscore/data/package.json
xstatic/pkg/underscore/data/underscore-min.js
xstatic/pkg/underscore/data/underscore-min.map
xstatic/pkg/underscore/data/underscore.js