Metadata-Version: 1.0
Name: XStatic-underscore
Version: 1.7.0.1
Summary: underscore 1.7.0 (XStatic packaging standard)
Home-page: https://github.com/jashkenas/underscore
Author: Richard Jones
Author-email: r1chardj0n3s@gmail.com
License: (same as underscore)
Keywords: util functional server client browser underscore xstatic
Platform: any
